rtl/status_value_logic.v
/*
 *  File:                   status_valid_logic.v
 *  Description:            Combinational logic for the vector update
 *  Project:                Status Valid Vector
 *  Author:                 Abraham J. Ruiz R. (https://github.com/m4j0rt0m)
 *  Revision:               0.1 - First version
 */
module status_value_logic
(/*AUTOARG*/
   // Outputs
   q_o,
   // Inputs
   push_i, pull_i, update_i, valid_i, carry_i, empty_i, value_i,
   next_i, actual_i
   );

  /* ports */
  input       push_i;   //..push a new entry
  input       pull_i;   //..pull an entry from queue
  input       update_i; //..update or not the status vector bit
  input       valid_i;  //..valid update mask bit (i)
  input       carry_i;  //..next update mask bit (i+1)
  input       empty_i;  //..empty status vector
  input       value_i;  //..state input
  input       next_i;   //..next bit in status vector (i+1)
  input       actual_i; //..actual registered bit in status vector (i)

  output reg  q_o;      //..bit to be registered in status vector (i)

  /* local parameters <push and pull> */
  localparam  NN        = 2'b00;  //..neither push nor pull (there is no change)
  localparam  NP        = 2'b01;  //..push and no pull
  localparam  PN        = 2'b10;  //..pull and no push
  localparam  PP        = 2'b11;  //..both push and pull

  /* update mask bits (working as tail pointers, head pointer always in [0]) */
  wire  update_en_a = update_i & ~valid_i;  //..update-bit enable (i), as a tail pointer
  wire  update_en_b = valid_i & ~carry_i;   //..update-bit enable (i+1), modified tail pointer

  /* logic */
  always @ (*) begin
    case({pull_i, push_i})
      NN:  begin  //..nothing happens
        q_o     = actual_i;
      end
      NP:  begin  //..push a new entry
        if(update_en_a)
          q_o = value_i;
        else
          q_o = actual_i;
      end
      PN:  begin  //..pull an entry
        q_o = next_i;
      end
      PP:  begin  //..push a new entry, as well, pull the oldest entry
        if(~empty_i) begin
          if(update_en_b)
            q_o = value_i;
          else
            q_o = next_i;
        end
        else
          q_o = value_i;
      end
    endcase
  end

endmodule // status_value_logic

rtl/status_value_vector.v
/*
 *  File:                   status_valid_vector.v
 *  Description:            Combinational logic for the vector update
 *  Project:                Status Value Vector
 *  Author:                 Abraham J. Ruiz R. (https://github.com/m4j0rt0m)
 *  Revision:               0.1 - First version
 */
module status_value_vector
# (
    parameter DEPTH = 16
  )
(/*AUTOARG*/
   // Outputs
   value_o, valid_o, full_o,
   // Inputs
   clk_i, rsn_i, push_i, pull_i, value_i
   );

  /* ports */
  input       clk_i;    //..clock signal
  input       rsn_i;    //..active low reset
  input       push_i;   //..push a new status entry
  input       pull_i;   //..pull the next oldest entry
  input       value_i;  //..update value
  output      value_o;  //..next value entry
  output      valid_o;  //..valid entry in the status vector
  output      full_o;   //..status vector is full

  /* integers and genvars */
  genvar I;

  /* regs and wires */
  wire              empty;
  wire  [DEPTH-1:0] nxt_vector_d;
  wire  [DEPTH-1:0] status_vector_d;
  wire  [DEPTH-1:0] update_vector_d;
  wire  [DEPTH-1:0] carry_vector_d;
  reg   [DEPTH-1:0] valid_vector_q;
  reg   [DEPTH-1:0] status_vector_q;

  /* empty/occupied vector */
  assign  empty           = ~valid_vector_q[0];

  /* expand vectors assignment */
  assign  nxt_vector_d    = {1'b0, status_vector_q[DEPTH-1:1]};
  assign  update_vector_d = {valid_vector_q[DEPTH-2:0], 1'b1};
  assign  carry_vector_d  = {1'b0, valid_vector_q[DEPTH-1:1]};

  /* valid vector */
  always @ (posedge clk_i, negedge rsn_i) begin
    if(~rsn_i)  //..asynchronous reset
      valid_vector_q <=  {DEPTH{1'b0}};
    else  begin
      case({pull_i,push_i})
        2'b01:  begin   //..shift to the left
          valid_vector_q[0]         <=  1'b1;
          valid_vector_q[DEPTH-1:1] <=  valid_vector_q[DEPTH-2:0];
        end
        2'b10:  begin   //..shift to the right
          valid_vector_q[DEPTH-2:0] <=  valid_vector_q[DEPTH-1:1];
          valid_vector_q[DEPTH-1]   <=  1'b0;
        end
        2'b11:  begin
          if(empty) begin
            valid_vector_q[0]         <=  1'b1;
            valid_vector_q[DEPTH-1:1] <=  valid_vector_q[DEPTH-2:0];
          end
          else
            valid_vector_q            <=  valid_vector_q;
        end
        default:  begin //..stays the same
          valid_vector_q <=  valid_vector_q;
        end
      endcase
    end
  end

  /* update-bit combinational logic */
  generate
    for(I=0; I<DEPTH; I=I+1)  begin:  comb_logic
      status_value_logic
        status_value_logic_inst (
            .push_i   (push_i),
            .pull_i   (pull_i),
            .update_i (update_vector_d[I]),
            .valid_i  (valid_vector_q[I]),
            .carry_i  (carry_vector_d[I]),
            .empty_i  (empty),
            .value_i  (value_i),
            .next_i   (nxt_vector_d[I]),
            .actual_i (status_vector_q[I]),
            .q_o      (status_vector_d[I])
          );
    end
  endgenerate

  /* status vector */
  always @ (posedge clk_i, negedge rsn_i) begin
    if(~rsn_i)
      status_vector_q <=  {DEPTH{1'b0}};
    else
      status_vector_q <=  status_vector_d;
  end

  /* output assignments */
  assign value_o  = status_vector_q[0];
  assign valid_o  = valid_vector_q[0];
  assign full_o   = valid_vector_q[DEPTH-1];

endmodule // status_value_vector

test_bench/status_value_vector_tb.v
/*
 *  File:                   status_value_vector_tb.v
 *  Description:            Test bench for status value vector module
 *  Project:                Status Value Vector
 *  Author:                 Abraham J. Ruiz R. (https://github.com/m4j0rt0m)
 *  Revision:               0.1 - First version
 */
module status_value_vector_tb ();


  /* local parameters */
  localparam  FREQ_CLK  = 50000000;
  localparam  CLK_F     = (1000000000 / FREQ_CLK) / 2;
  localparam  DEPTH     = 32;

    /* defines */
  `define CYCLES(cycles)  (CLK_F*2*cycles)

  /* regs and wires */
  reg   clk_i;    //..clock signal
  reg   rsn_i;    //..active low reset
  reg   push_i;   //..push a new status entry
  reg   pull_i;   //..pull the next oldest entry
  reg   value_i;  //..value to be inserted into queue
  wire  value_o;  //..next value from status vector
  wire  valid_o;  //..valid entry in the status vector
  wire  full_o;   //..status vector is full

  /* dut */
  status_value_vector
    # (
        .DEPTH  (DEPTH)
      )
    dut (
        .clk_i (clk_i),
        .rsn_i (rsn_i),
        .push_i (push_i),
        .pull_i (pull_i),
        .value_i (value_i),
        .value_o (value_o),
        .valid_o (valid_o),
        .full_o (full_o)
      );

  /* initial */
  initial begin
    clk_i   = 0;
    rsn_i   = 0;
    push_i  = 0;
    pull_i  = 0;
    value_i = 0;
  end

  /* clock signal */
  always  begin
    #CLK_F  clk_i <=  ~clk_i;
  end

  /* simulation */
  always  begin
    $dumpfile("status_value_vector.vcd");
    $dumpvars();
    #`CYCLES(4)   rsn_i = 1;
    #`CYCLES(1)   push_i  = 1;
                  value_i = 1;
    #`CYCLES(4)   push_i  = 0;
                  pull_i  = 1;
    #`CYCLES(5)   push_i  = 1;
                  value_i = 0;
    #`CYCLES(2)   value_i = 1;
    #`CYCLES(4)   push_i  = 0;
                  value_i = 0;
    #`CYCLES(32)  $finish;
  end

endmodule // status_value_vector_tb

build/status_value_vector.vcd
$date
	Tue Jul  9 17:27:13 2019
$end
$version
	Icarus Verilog
$end
$timescale
	1s
$end
$scope module status_value_vector_tb $end
$var wire 1 ! value_o $end
$var wire 1 " valid_o $end
$var wire 1 # full_o $end
$var reg 1 $ clk_i $end
$var reg 1 % pull_i $end
$var reg 1 & push_i $end
$var reg 1 ' rsn_i $end
$var reg 1 ( value_i $end
$scope module dut $end
$var wire 1 $ clk_i $end
$var wire 1 ) empty $end
$var wire 1 % pull_i $end
$var wire 1 & push_i $end
$var wire 1 ' rsn_i $end
$var wire 1 ( value_i $end
$var wire 1 ! value_o $end
$var wire 1 " valid_o $end
$var wire 32 * update_vector_d [31:0] $end
$var wire 32 + status_vector_d [31:0] $end
$var wire 32 , nxt_vector_d [31:0] $end
$var wire 1 # full_o $end
$var wire 32 - carry_vector_d [31:0] $end
$var reg 32 . status_vector_q [31:0] $end
$var reg 32 / valid_vector_q [31:0] $end
$scope begin comb_logic[0] $end
$scope module status_value_logic_inst $end
$var wire 1 0 actual_i $end
$var wire 1 1 carry_i $end
$var wire 1 ) empty_i $end
$var wire 1 2 next_i $end
$var wire 1 % pull_i $end
$var wire 1 & push_i $end
$var wire 1 3 update_en_a $end
$var wire 1 4 update_en_b $end
$var wire 1 5 update_i $end
$var wire 1 6 valid_i $end
$var wire 1 ( value_i $end
$var reg 1 7 q_o $end
$upscope $end
$upscope $end
$scope begin comb_logic[1] $end
$scope module status_value_logic_inst $end
$var wire 1 8 actual_i $end
$var wire 1 9 carry_i $end
$var wire 1 ) empty_i $end
$var wire 1 : next_i $end
$var wire 1 % pull_i $end
$var wire 1 & push_i $end
$var wire 1 ; update_en_a $end
$var wire 1 < update_en_b $end
$var wire 1 = update_i $end
$var wire 1 > valid_i $end
$var wire 1 ( value_i $end
$var reg 1 ? q_o $end
$upscope $end
$upscope $end
$scope begin comb_logic[2] $end
$scope module status_value_logic_inst $end
$var wire 1 @ actual_i $end
$var wire 1 A carry_i $end
$var wire 1 ) empty_i $end
$var wire 1 B next_i $end
$var wire 1 % pull_i $end
$var wire 1 & push_i $end
$var wire 1 C update_en_a $end
$var wire 1 D update_en_b $end
$var wire 1 E update_i $end
$var wire 1 F valid_i $end
$var wire 1 ( value_i $end
$var reg 1 G q_o $end
$upscope $end
$upscope $end
$scope begin comb_logic[3] $end
$scope module status_value_logic_inst $end
$var wire 1 H actual_i $end
$var wire 1 I carry_i $end
$var wire 1 ) empty_i $end
$var wire 1 J next_i $end
$var wire 1 % pull_i $end
$var wire 1 & push_i $end
$var wire 1 K update_en_a $end
$var wire 1 L update_en_b $end
$var wire 1 M update_i $end
$var wire 1 N valid_i $end
$var wire 1 ( value_i $end
$var reg 1 O q_o $end
$upscope $end
$upscope $end
$scope begin comb_logic[4] $end
$scope module status_value_logic_inst $end
$var wire 1 P actual_i $end
$var wire 1 Q carry_i $end
$var wire 1 ) empty_i $end
$var wire 1 R next_i $end
$var wire 1 % pull_i $end
$var wire 1 & push_i $end
$var wire 1 S update_en_a $end
$var wire 1 T update_en_b $end
$var wire 1 U update_i $end
$var wire 1 V valid_i $end
$var wire 1 ( value_i $end
$var reg 1 W q_o $end
$upscope $end
$upscope $end
$scope begin comb_logic[5] $end
$scope module status_value_logic_inst $end
$var wire 1 X actual_i $end
$var wire 1 Y carry_i $end
$var wire 1 ) empty_i $end
$var wire 1 Z next_i $end
$var wire 1 % pull_i $end
$var wire 1 & push_i $end
$var wire 1 [ update_en_a $end
$var wire 1 \ update_en_b $end
$var wire 1 ] update_i $end
$var wire 1 ^ valid_i $end
$var wire 1 ( value_i $end
$var reg 1 _ q_o $end
$upscope $end
$upscope $end
$scope begin comb_logic[6] $end
$scope module status_value_logic_inst $end
$var wire 1 ` actual_i $end
$var wire 1 a carry_i $end
$var wire 1 ) empty_i $end
$var wire 1 b next_i $end
$var wire 1 % pull_i $end
$var wire 1 & push_i $end
$var wire 1 c update_en_a $end
$var wire 1 d update_en_b $end
$var wire 1 e update_i $end
$var wire 1 f valid_i $end
$var wire 1 ( value_i $end
$var reg 1 g q_o $end
$upscope $end
$upscope $end
$scope begin comb_logic[7] $end
$scope module status_value_logic_inst $end
$var wire 1 h actual_i $end
$var wire 1 i carry_i $end
$var wire 1 ) empty_i $end
$var wire 1 j next_i $end
$var wire 1 % pull_i $end
$var wire 1 & push_i $end
$var wire 1 k update_en_a $end
$var wire 1 l update_en_b $end
$var wire 1 m update_i $end
$var wire 1 n valid_i $end
$var wire 1 ( value_i $end
$var reg 1 o q_o $end
$upscope $end
$upscope $end
$scope begin comb_logic[8] $end
$scope module status_value_logic_inst $end
$var wire 1 p actual_i $end
$var wire 1 q carry_i $end
$var wire 1 ) empty_i $end
$var wire 1 r next_i $end
$var wire 1 % pull_i $end
$var wire 1 & push_i $end
$var wire 1 s update_en_a $end
$var wire 1 t update_en_b $end
$var wire 1 u update_i $end
$var wire 1 v valid_i $end
$var wire 1 ( value_i $end
$var reg 1 w q_o $end
$upscope $end
$upscope $end
$scope begin comb_logic[9] $end
$scope module status_value_logic_inst $end
$var wire 1 x actual_i $end
$var wire 1 y carry_i $end
$var wire 1 ) empty_i $end
$var wire 1 z next_i $end
$var wire 1 % pull_i $end
$var wire 1 & push_i $end
$var wire 1 { update_en_a $end
$var wire 1 | update_en_b $end
$var wire 1 } update_i $end
$var wire 1 ~ valid_i $end
$var wire 1 ( value_i $end
$var reg 1 !" q_o $end
$upscope $end
$upscope $end
$scope begin comb_logic[10] $end
$scope module status_value_logic_inst $end
$var wire 1 "" actual_i $end
$var wire 1 #" carry_i $end
$var wire 1 ) empty_i $end
$var wire 1 $" next_i $end
$var wire 1 % pull_i $end
$var wire 1 & push_i $end
$var wire 1 %" update_en_a $end
$var wire 1 &" update_en_b $end
$var wire 1 '" update_i $end
$var wire 1 (" valid_i $end
$var wire 1 ( value_i $end
$var reg 1 )" q_o $end
$upscope $end
$upscope $end
$scope begin comb_logic[11] $end
$scope module status_value_logic_inst $end
$var wire 1 *" actual_i $end
$var wire 1 +" carry_i $end
$var wire 1 ) empty_i $end
$var wire 1 ," next_i $end
$var wire 1 % pull_i $end
$var wire 1 & push_i $end
$var wire 1 -" update_en_a $end
$var wire 1 ." update_en_b $end
$var wire 1 /" update_i $end
$var wire 1 0" valid_i $end
$var wire 1 ( value_i $end
$var reg 1 1" q_o $end
$upscope $end
$upscope $end
$scope begin comb_logic[12] $end
$scope module status_value_logic_inst $end
$var wire 1 2" actual_i $end
$var wire 1 3" carry_i $end
$var wire 1 ) empty_i $end
$var wire 1 4" next_i $end
$var wire 1 % pull_i $end
$var wire 1 & push_i $end
$var wire 1 5" update_en_a $end
$var wire 1 6" update_en_b $end
$var wire 1 7" update_i $end
$var wire 1 8" valid_i $end
$var wire 1 ( value_i $end
$var reg 1 9" q_o $end
$upscope $end
$upscope $end
$scope begin comb_logic[13] $end
$scope module status_value_logic_inst $end
$var wire 1 :" actual_i $end
$var wire 1 ;" carry_i $end
$var wire 1 ) empty_i $end
$var wire 1 <" next_i $end
$var wire 1 % pull_i $end
$var wire 1 & push_i $end
$var wire 1 =" update_en_a $end
$var wire 1 >" update_en_b $end
$var wire 1 ?" update_i $end
$var wire 1 @" valid_i $end
$var wire 1 ( value_i $end
$var reg 1 A" q_o $end
$upscope $end
$upscope $end
$scope begin comb_logic[14] $end
$scope module status_value_logic_inst $end
$var wire 1 B" actual_i $end
$var wire 1 C" carry_i $end
$var wire 1 ) empty_i $end
$var wire 1 D" next_i $end
$var wire 1 % pull_i $end
$var wire 1 & push_i $end
$var wire 1 E" update_en_a $end
$var wire 1 F" update_en_b $end
$var wire 1 G" update_i $end
$var wire 1 H" valid_i $end
$var wire 1 ( value_i $end
$var reg 1 I" q_o $end
$upscope $end
$upscope $end
$scope begin comb_logic[15] $end
$scope module status_value_logic_inst $end
$var wire 1 J" actual_i $end
$var wire 1 K" carry_i $end
$var wire 1 ) empty_i $end
$var wire 1 L" next_i $end
$var wire 1 % pull_i $end
$var wire 1 & push_i $end
$var wire 1 M" update_en_a $end
$var wire 1 N" update_en_b $end
$var wire 1 O" update_i $end
$var wire 1 P" valid_i $end
$var wire 1 ( value_i $end
$var reg 1 Q" q_o $end
$upscope $end
$upscope $end
$scope begin comb_logic[16] $end
$scope module status_value_logic_inst $end
$var wire 1 R" actual_i $end
$var wire 1 S" carry_i $end
$var wire 1 ) empty_i $end
$var wire 1 T" next_i $end
$var wire 1 % pull_i $end
$var wire 1 & push_i $end
$var wire 1 U" update_en_a $end
$var wire 1 V" update_en_b $end
$var wire 1 W" update_i $end
$var wire 1 X" valid_i $end
$var wire 1 ( value_i $end
$var reg 1 Y" q_o $end
$upscope $end
$upscope $end
$scope begin comb_logic[17] $end
$scope module status_value_logic_inst $end
$var wire 1 Z" actual_i $end
$var wire 1 [" carry_i $end
$var wire 1 ) empty_i $end
$var wire 1 \" next_i $end
$var wire 1 % pull_i $end
$var wire 1 & push_i $end
$var wire 1 ]" update_en_a $end
$var wire 1 ^" update_en_b $end
$var wire 1 _" update_i $end
$var wire 1 `" valid_i $end
$var wire 1 ( value_i $end
$var reg 1 a" q_o $end
$upscope $end
$upscope $end
$scope begin comb_logic[18] $end
$scope module status_value_logic_inst $end
$var wire 1 b" actual_i $end
$var wire 1 c" carry_i $end
$var wire 1 ) empty_i $end
$var wire 1 d" next_i $end
$var wire 1 % pull_i $end
$var wire 1 & push_i $end
$var wire 1 e" update_en_a $end
$var wire 1 f" update_en_b $end
$var wire 1 g" update_i $end
$var wire 1 h" valid_i $end
$var wire 1 ( value_i $end
$var reg 1 i" q_o $end
$upscope $end
$upscope $end
$scope begin comb_logic[19] $end
$scope module status_value_logic_inst $end
$var wire 1 j" actual_i $end
$var wire 1 k" carry_i $end
$var wire 1 ) empty_i $end
$var wire 1 l" next_i $end
$var wire 1 % pull_i $end
$var wire 1 & push_i $end
$var wire 1 m" update_en_a $end
$var wire 1 n" update_en_b $end
$var wire 1 o" update_i $end
$var wire 1 p" valid_i $end
$var wire 1 ( value_i $end
$var reg 1 q" q_o $end
$upscope $end
$upscope $end
$scope begin comb_logic[20] $end
$scope module status_value_logic_inst $end
$var wire 1 r" actual_i $end
$var wire 1 s" carry_i $end
$var wire 1 ) empty_i $end
$var wire 1 t" next_i $end
$var wire 1 % pull_i $end
$var wire 1 & push_i $end
$var wire 1 u" update_en_a $end
$var wire 1 v" update_en_b $end
$var wire 1 w" update_i $end
$var wire 1 x" valid_i $end
$var wire 1 ( value_i $end
$var reg 1 y" q_o $end
$upscope $end
$upscope $end
$scope begin comb_logic[21] $end
$scope module status_value_logic_inst $end
$var wire 1 z" actual_i $end
$var wire 1 {" carry_i $end
$var wire 1 ) empty_i $end
$var wire 1 |" next_i $end
$var wire 1 % pull_i $end
$var wire 1 & push_i $end
$var wire 1 }" update_en_a $end
$var wire 1 ~" update_en_b $end
$var wire 1 !# update_i $end
$var wire 1 "# valid_i $end
$var wire 1 ( value_i $end
$var reg 1 ## q_o $end
$upscope $end
$upscope $end
$scope begin comb_logic[22] $end
$scope module status_value_logic_inst $end
$var wire 1 $# actual_i $end
$var wire 1 %# carry_i $end
$var wire 1 ) empty_i $end
$var wire 1 &# next_i $end
$var wire 1 % pull_i $end
$var wire 1 & push_i $end
$var wire 1 '# update_en_a $end
$var wire 1 (# update_en_b $end
$var wire 1 )# update_i $end
$var wire 1 *# valid_i $end
$var wire 1 ( value_i $end
$var reg 1 +# q_o $end
$upscope $end
$upscope $end
$scope begin comb_logic[23] $end
$scope module status_value_logic_inst $end
$var wire 1 ,# actual_i $end
$var wire 1 -# carry_i $end
$var wire 1 ) empty_i $end
$var wire 1 .# next_i $end
$var wire 1 % pull_i $end
$var wire 1 & push_i $end
$var wire 1 /# update_en_a $end
$var wire 1 0# update_en_b $end
$var wire 1 1# update_i $end
$var wire 1 2# valid_i $end
$var wire 1 ( value_i $end
$var reg 1 3# q_o $end
$upscope $end
$upscope $end
$scope begin comb_logic[24] $end
$scope module status_value_logic_inst $end
$var wire 1 4# actual_i $end
$var wire 1 5# carry_i $end
$var wire 1 ) empty_i $end
$var wire 1 6# next_i $end
$var wire 1 % pull_i $end
$var wire 1 & push_i $end
$var wire 1 7# update_en_a $end
$var wire 1 8# update_en_b $end
$var wire 1 9# update_i $end
$var wire 1 :# valid_i $end
$var wire 1 ( value_i $end
$var reg 1 ;# q_o $end
$upscope $end
$upscope $end
$scope begin comb_logic[25] $end
$scope module status_value_logic_inst $end
$var wire 1 <# actual_i $end
$var wire 1 =# carry_i $end
$var wire 1 ) empty_i $end
$var wire 1 ># next_i $end
$var wire 1 % pull_i $end
$var wire 1 & push_i $end
$var wire 1 ?# update_en_a $end
$var wire 1 @# update_en_b $end
$var wire 1 A# update_i $end
$var wire 1 B# valid_i $end
$var wire 1 ( value_i $end
$var reg 1 C# q_o $end
$upscope $end
$upscope $end
$scope begin comb_logic[26] $end
$scope module status_value_logic_inst $end
$var wire 1 D# actual_i $end
$var wire 1 E# carry_i $end
$var wire 1 ) empty_i $end
$var wire 1 F# next_i $end
$var wire 1 % pull_i $end
$var wire 1 & push_i $end
$var wire 1 G# update_en_a $end
$var wire 1 H# update_en_b $end
$var wire 1 I# update_i $end
$var wire 1 J# valid_i $end
$var wire 1 ( value_i $end
$var reg 1 K# q_o $end
$upscope $end
$upscope $end
$scope begin comb_logic[27] $end
$scope module status_value_logic_inst $end
$var wire 1 L# actual_i $end
$var wire 1 M# carry_i $end
$var wire 1 ) empty_i $end
$var wire 1 N# next_i $end
$var wire 1 % pull_i $end
$var wire 1 & push_i $end
$var wire 1 O# update_en_a $end
$var wire 1 P# update_en_b $end
$var wire 1 Q# update_i $end
$var wire 1 R# valid_i $end
$var wire 1 ( value_i $end
$var reg 1 S# q_o $end
$upscope $end
$upscope $end
$scope begin comb_logic[28] $end
$scope module status_value_logic_inst $end
$var wire 1 T# actual_i $end
$var wire 1 U# carry_i $end
$var wire 1 ) empty_i $end
$var wire 1 V# next_i $end
$var wire 1 % pull_i $end
$var wire 1 & push_i $end
$var wire 1 W# update_en_a $end
$var wire 1 X# update_en_b $end
$var wire 1 Y# update_i $end
$var wire 1 Z# valid_i $end
$var wire 1 ( value_i $end
$var reg 1 [# q_o $end
$upscope $end
$upscope $end
$scope begin comb_logic[29] $end
$scope module status_value_logic_inst $end
$var wire 1 \# actual_i $end
$var wire 1 ]# carry_i $end
$var wire 1 ) empty_i $end
$var wire 1 ^# next_i $end
$var wire 1 % pull_i $end
$var wire 1 & push_i $end
$var wire 1 _# update_en_a $end
$var wire 1 `# update_en_b $end
$var wire 1 a# update_i $end
$var wire 1 b# valid_i $end
$var wire 1 ( value_i $end
$var reg 1 c# q_o $end
$upscope $end
$upscope $end
$scope begin comb_logic[30] $end
$scope module status_value_logic_inst $end
$var wire 1 d# actual_i $end
$var wire 1 e# carry_i $end
$var wire 1 ) empty_i $end
$var wire 1 f# next_i $end
$var wire 1 % pull_i $end
$var wire 1 & push_i $end
$var wire 1 g# update_en_a $end
$var wire 1 h# update_en_b $end
$var wire 1 i# update_i $end
$var wire 1 j# valid_i $end
$var wire 1 ( value_i $end
$var reg 1 k# q_o $end
$upscope $end
$upscope $end
$scope begin comb_logic[31] $end
$scope module status_value_logic_inst $end
$var wire 1 l# actual_i $end
$var wire 1 m# carry_i $end
$var wire 1 ) empty_i $end
$var wire 1 n# next_i $end
$var wire 1 % pull_i $end
$var wire 1 & push_i $end
$var wire 1 o# update_en_a $end
$var wire 1 p# update_en_b $end
$var wire 1 q# update_i $end
$var wire 1 r# valid_i $end
$var wire 1 ( value_i $end
$var reg 1 s# q_o $end
$upscope $end
$upscope $end
$upscope $end
$upscope $end
$enddefinitions $end
#0
$dumpvars
0s#
0r#
0q#
0p#
0o#
0n#
0m#
0l#
0k#
0j#
0i#
0h#
0g#
0f#
0e#
0d#
0c#
0b#
0a#
0`#
0_#
0^#
0]#
0\#
0[#
0Z#
0Y#
0X#
0W#
0V#
0U#
0T#
0S#
0R#
0Q#
0P#
0O#
0N#
0M#
0L#
0K#
0J#
0I#
0H#
0G#
0F#
0E#
0D#
0C#
0B#
0A#
0@#
0?#
0>#
0=#
0<#
0;#
0:#
09#
08#
07#
06#
05#
04#
03#
02#
01#
00#
0/#
0.#
0-#
0,#
0+#
0*#
0)#
0(#
0'#
0&#
0%#
0$#
0##
0"#
0!#
0~"
0}"
0|"
0{"
0z"
0y"
0x"
0w"
0v"
0u"
0t"
0s"
0r"
0q"
0p"
0o"
0n"
0m"
0l"
0k"
0j"
0i"
0h"
0g"
0f"
0e"
0d"
0c"
0b"
0a"
0`"
0_"
0^"
0]"
0\"
0["
0Z"
0Y"
0X"
0W"
0V"
0U"
0T"
0S"
0R"
0Q"
0P"
0O"
0N"
0M"
0L"
0K"
0J"
0I"
0H"
0G"
0F"
0E"
0D"
0C"
0B"
0A"
0@"
0?"
0>"
0="
0<"
0;"
0:"
09"
08"
07"
06"
05"
04"
03"
02"
01"
00"
0/"
0."
0-"
0,"
0+"
0*"
0)"
0("
0'"
0&"
0%"
0$"
0#"
0""
0!"
0~
0}
0|
0{
0z
0y
0x
0w
0v
0u
0t
0s
0r
0q
0p
0o
0n
0m
0l
0k
0j
0i
0h
0g
0f
0e
0d
0c
0b
0a
0`
0_
0^
0]
0\
0[
0Z
0Y
0X
0W
0V
0U
0T
0S
0R
0Q
0P
0O
0N
0M
0L
0K
0J
0I
0H
0G
0F
0E
0D
0C
0B
0A
0@
0?
0>
0=
0<
0;
0:
09
08
07
06
15
04
13
02
01
00
b0 /
b0 .
b0 -
b0 ,
b0 +
b1 *
1)
0(
0'
0&
0%
0$
0#
0"
0!
$end
#10
1$
#20
0$
#30
1$
#40
0$
#50
1$
#60
0$
#70
1$
#80
0$
1'
#90
1$
#100
0$
b1 +
17
1(
1&
#110
03
b11 +
1?
1;
14
0)
1=
16
b11 *
1"
10
1!
b1 /
b1 .
1$
#120
0$
#130
b111 +
1G
04
0;
1C
12
1<
1E
11
18
b1 ,
1>
b111 *
b1 -
b11 .
b11 /
1$
#140
0$
#150
b1111 +
1O
0<
0C
1K
1D
1M
19
1:
1F
b1111 *
b11 -
1@
b11 ,
b111 /
b111 .
1$
#160
0$
#170
b11111 +
1W
0D
0K
1S
1B
1L
1U
1A
1H
b111 ,
1N
b11111 *
b111 -
b1111 .
b1111 /
1$
#180
0$
0O
b111 +
0W
1%
0&
#190
1D
1K
0S
b11 +
0G
0L
0U
0A
0B
0N
b1111 *
b11 -
0H
b11 ,
b111 /
b111 .
1$
#200
0$
#210
1<
b1 +
0?
1C
0K
0:
0D
0M
09
0@
b1 ,
0F
b111 *
b1 -
b11 .
b11 /
1$
#220
0$
#230
14
1;
0C
b0 +
07
0<
0E
01
02
0>
b11 *
b0 -
08
b0 ,
b1 /
b1 .
1$
#240
0$
#250
13
0;
04
1)
0=
00
0!
06
b1 *
0"
b0 .
b0 /
1$
#260
0$
#270
1$
#280
0$
0(
1&
#290
03
1;
14
0)
1=
16
b11 *
1"
b1 /
1$
#300
0$
#310
1$
#320
0$
b1 +
17
1(
#330
10
1!
b1 .
1$
#340
0$
#350
1$
#360
0$
#370
1$
#380
0$
#390
1$
#400
0$
b0 +
07
0(
0&
#410
13
0;
04
1)
0=
00
0!
06
b1 *
0"
b0 .
b0 /
1$
